autoeda/__init__.py
autoeda/__main__.py
autoeda/_argument_parser.py
autoeda/_version.py
autoeda-0.0.dist-info/AUTHORS.md
autoeda-0.0.dist-info/LICENSE
autoeda-0.0.dist-info/METADATA
autoeda-0.0.dist-info/WHEEL
autoeda-0.0.dist-info/entry_points.txt
autoeda-0.0.dist-info/top_level.txt
autoeda-0.0.dist-info/RECORD
