Metadata-Version: 2.1
Name: autoeda
Version: 0.0
Summary: My module description
Home-page: https://github.com/guiferviz/autoeda
Author: guiferviz
Author-email: guiferviz@gmail.com
License: Copyright guiferviz
Keywords: python library code
Platform: UNKNOWN
